uat/__init__.py
uat/apply.py
uat/create.py
uat-0.2.0.dist-info/LICENSE
uat-0.2.0.dist-info/METADATA
uat-0.2.0.dist-info/WHEEL
uat-0.2.0.dist-info/RECORD
