Metadata-Version: 2.1
Name: uat
Version: 0.2.0
Summary: Universal Approximation Theorem in JAX
License: MIT
Author: Ivan Dustin Bilon
Author-email: ivan22.dust@gmail.com
Requires-Python: >=3.9,<4.0
Classifier: License :: OSI Approved :: MIT License
Classifier: Programming Language :: Python :: 3
Classifier: Programming Language :: Python :: 3.9
Classifier: Programming Language :: Python :: 3.10
Classifier: Programming Language :: Python :: 3.11
Classifier: Programming Language :: Python :: 3.12
Requires-Dist: jax (>=0.4.30,<0.5.0)
